README.md
setup.py
docker_map.egg-info/PKG-INFO
docker_map.egg-info/SOURCES.txt
docker_map.egg-info/dependency_links.txt
docker_map.egg-info/requires.txt
docker_map.egg-info/top_level.txt
dockermap/__init__.py
dockermap/api.py
dockermap/dep.py
dockermap/docker_api.py
dockermap/exceptions.py
dockermap/functional.py
dockermap/shortcuts.py
dockermap/utils.py
dockermap/build/__init__.py
dockermap/build/buffer.py
dockermap/build/context.py
dockermap/build/dockerfile.py
dockermap/client/__init__.py
dockermap/client/base.py
dockermap/client/cli.py
dockermap/client/docker_util.py
dockermap/map/__init__.py
dockermap/map/client.py
dockermap/map/exceptions.py
dockermap/map/input.py
dockermap/map/yaml.py
dockermap/map/action/__init__.py
dockermap/map/action/base.py
dockermap/map/action/resume.py
dockermap/map/action/script.py
dockermap/map/action/simple.py
dockermap/map/action/update.py
dockermap/map/config/__init__.py
dockermap/map/config/client.py
dockermap/map/config/container.py
dockermap/map/config/host_volume.py
dockermap/map/config/main.py
dockermap/map/config/network.py
dockermap/map/config/utils.py
dockermap/map/config/volume.py
dockermap/map/policy/__init__.py
dockermap/map/policy/base.py
dockermap/map/policy/cache.py
dockermap/map/policy/dep.py
dockermap/map/policy/utils.py
dockermap/map/runner/__init__.py
dockermap/map/runner/attached.py
dockermap/map/runner/base.py
dockermap/map/runner/cmd.py
dockermap/map/runner/image.py
dockermap/map/runner/network.py
dockermap/map/runner/script.py
dockermap/map/runner/signal_stop.py
dockermap/map/runner/utils.py
dockermap/map/state/__init__.py
dockermap/map/state/base.py
dockermap/map/state/initial.py
dockermap/map/state/utils.py
dockermap/map/state/update/__init__.py
dockermap/map/state/update/container.py
dockermap/map/state/update/main.py
dockermap/map/state/update/network.py
dockermap/map/state/update/volume.py
tests/__init__.py
tests/test_cli.py
tests/test_config.py
tests/test_context.py
tests/test_dependency_resolution.py
tests/test_input.py
tests/test_policy_kwargs.py
tests/test_shortcuts.py
tests/test_state.py
tests/test_value_resolution.py