Metadata-Version: 2.1
Name: docker-map
Version: 1.1.1
Summary: Managing Docker images, containers, and their dependencies in Python.
Home-page: https://github.com/merll/docker-map
Author: Matthias Erll
Author-email: matthias@erll.de
License: MIT
Keywords: docker,deployment
Platform: OS Independent
Classifier: Environment :: Web Environment
Classifier: Intended Audience :: Developers
Classifier: License :: OSI Approved :: MIT License
Classifier: Operating System :: OS Independent
Classifier: Programming Language :: Python
Classifier: Topic :: Software Development :: Libraries :: Python Modules
Classifier: Topic :: Software Development :: Build Tools
Classifier: Topic :: System :: Software Distribution
Classifier: Development Status :: 5 - Production/Stable
Classifier: Programming Language :: Python :: 2.7
Classifier: Programming Language :: Python :: 3.4
Classifier: Programming Language :: Python :: 3.5
Classifier: Programming Language :: Python :: 3.6
Classifier: Programming Language :: Python :: 3.7
Provides-Extra: yaml
Provides-Extra: legacy
Provides-Extra: docker
